awslabs/__init__.py
awslabs/redshift_mcp_server/__init__.py
awslabs/redshift_mcp_server/consts.py
awslabs/redshift_mcp_server/models.py
awslabs/redshift_mcp_server/redshift.py
awslabs/redshift_mcp_server/server.py
awslabs_redshift_mcp_server-0.0.15.dist-info/METADATA
awslabs_redshift_mcp_server-0.0.15.dist-info/WHEEL
awslabs_redshift_mcp_server-0.0.15.dist-info/entry_points.txt
awslabs_redshift_mcp_server-0.0.15.dist-info/licenses/LICENSE
awslabs_redshift_mcp_server-0.0.15.dist-info/licenses/NOTICE
awslabs_redshift_mcp_server-0.0.15.dist-info/RECORD
